{
  "m_GameObject": {
    "m_FileID": 0,
    "m_PathID": 8108998748969245066
  },
  "m_Enabled": 1,
  "m_Script": {
    "m_FileID": 0,
    "m_PathID": 1698654179331943719
  },
  "m_Name": "",
  "playableAnimator": {
    "m_FileID": 0,
    "m_PathID": 0
  },
  "animationStates": [
    {
      "priority": 0,
      "interruptibleBehaviour": 1,
      "forceSingleFrameAdvance": 0,
      "isUpgradeAnimation": 0,
      "animationClip": {
        "m_FileID": 0,
        "m_PathID": -836152202952009636
      },
      "eventTrigger": {
        "m_PersistentCalls": {
          "m_Calls": []
        }
      },
      "looping": 0,
      "importantFrames": [],
      "firstFrameReturns": [],
      "lastFrameReturns": []
    },
    {
      "priority": 1,
      "interruptibleBehaviour": 0,
      "forceSingleFrameAdvance": 0,
      "isUpgradeAnimation": 0,
      "animationClip": {
        "m_FileID": 0,
        "m_PathID": -836152203090848798
      },
      "eventTrigger": {
        "m_PersistentCalls": {
          "m_Calls": []
        }
      },
      "looping": 0,
      "importantFrames": [
        0.121058822
      ],
      "firstFrameReturns": [
        0.320301443
      ],
      "lastFrameReturns": []
    }
  ],
  "animationStatesByIndex": [],
  "placementConfigs": [
    {
      "priority": 10,
      "interruptibleBehaviour": 0,
      "forceSingleFrameAdvance": 0,
      "isUpgradeAnimation": 0,
      "animationClip": {
        "m_FileID": 0,
        "m_PathID": -836152200362752686
      },
      "eventTrigger": {
        "m_PersistentCalls": {
          "m_Calls": []
        }
      },
      "looping": 0,
      "importantFrames": [],
      "firstFrameReturns": [],
      "lastFrameReturns": []
    }
  ],
  "attackIdleConfigs": [
    {
      "priority": 0,
      "interruptibleBehaviour": 0,
      "forceSingleFrameAdvance": 0,
      "isUpgradeAnimation": 0,
      "animationClip": {
        "m_FileID": 0,
        "m_PathID": -836152201781930151
      },
      "eventTrigger": {
        "m_PersistentCalls": {
          "m_Calls": []
        }
      },
      "looping": 0,
      "importantFrames": [],
      "firstFrameReturns": [],
      "lastFrameReturns": []
    }
  ],
  "IdleVariants": [
    {
      "priority": 0,
      "interruptibleBehaviour": 0,
      "forceSingleFrameAdvance": 0,
      "isUpgradeAnimation": 0,
      "animationClip": {
        "m_FileID": 0,
        "m_PathID": -836152203203590482
      },
      "eventTrigger": {
        "m_PersistentCalls": {
          "m_Calls": []
        }
      },
      "looping": 0,
      "importantFrames": [],
      "firstFrameReturns": [],
      "lastFrameReturns": [],
      "variantWeight": 0.5
    },
    {
      "priority": 0,
      "interruptibleBehaviour": 0,
      "forceSingleFrameAdvance": 0,
      "isUpgradeAnimation": 0,
      "animationClip": {
        "m_FileID": 0,
        "m_PathID": -836152204108174102
      },
      "eventTrigger": {
        "m_PersistentCalls": {
          "m_Calls": []
        }
      },
      "looping": 0,
      "importantFrames": [],
      "firstFrameReturns": [],
      "lastFrameReturns": [],
      "variantWeight": 0.5
    }
  ]
}