{
  "m_GameObject": {
    "m_FileID": 0,
    "m_PathID": -4324787046446246945
  },
  "m_Enabled": 1,
  "m_Script": {
    "m_FileID": 0,
    "m_PathID": 1698654179331943719
  },
  "m_Name": "",
  "playableAnimator": {
    "m_FileID": 0,
    "m_PathID": 0
  },
  "animationStates": [
    {
      "priority": 0,
      "interruptibleBehaviour": 1,
      "forceSingleFrameAdvance": 0,
      "isUpgradeAnimation": 0,
      "animationClip": {
        "m_FileID": 0,
        "m_PathID": 3772127993343214950
      },
      "eventTrigger": {
        "m_PersistentCalls": {
          "m_Calls": []
        }
      },
      "looping": 0,
      "importantFrames": [],
      "firstFrameReturns": [],
      "lastFrameReturns": []
    },
    {
      "priority": 1,
      "interruptibleBehaviour": 3,
      "forceSingleFrameAdvance": 0,
      "isUpgradeAnimation": 0,
      "animationClip": {
        "m_FileID": 0,
        "m_PathID": 8242178286591870067
      },
      "eventTrigger": {
        "m_PersistentCalls": {
          "m_Calls": []
        }
      },
      "looping": 0,
      "importantFrames": [],
      "firstFrameReturns": [],
      "lastFrameReturns": []
    },
    {
      "priority": 1,
      "interruptibleBehaviour": 3,
      "forceSingleFrameAdvance": 0,
      "isUpgradeAnimation": 0,
      "animationClip": {
        "m_FileID": 0,
        "m_PathID": -6612376668672809722
      },
      "eventTrigger": {
        "m_PersistentCalls": {
          "m_Calls": []
        }
      },
      "looping": 0,
      "importantFrames": [],
      "firstFrameReturns": [],
      "lastFrameReturns": []
    },
    {
      "priority": 1,
      "interruptibleBehaviour": 3,
      "forceSingleFrameAdvance": 0,
      "isUpgradeAnimation": 0,
      "animationClip": {
        "m_FileID": 0,
        "m_PathID": -6390411106562814551
      },
      "eventTrigger": {
        "m_PersistentCalls": {
          "m_Calls": []
        }
      },
      "looping": 0,
      "importantFrames": [],
      "firstFrameReturns": [],
      "lastFrameReturns": []
    },
    {
      "priority": 1,
      "interruptibleBehaviour": 3,
      "forceSingleFrameAdvance": 0,
      "isUpgradeAnimation": 0,
      "animationClip": {
        "m_FileID": 0,
        "m_PathID": 5234023443996943379
      },
      "eventTrigger": {
        "m_PersistentCalls": {
          "m_Calls": []
        }
      },
      "looping": 0,
      "importantFrames": [],
      "firstFrameReturns": [],
      "lastFrameReturns": []
    }
  ],
  "animationStatesByIndex": [],
  "placementConfigs": [],
  "attackIdleConfigs": [
    {
      "priority": 0,
      "interruptibleBehaviour": 1,
      "forceSingleFrameAdvance": 0,
      "isUpgradeAnimation": 0,
      "animationClip": {
        "m_FileID": 0,
        "m_PathID": 3772127993343214950
      },
      "eventTrigger": {
        "m_PersistentCalls": {
          "m_Calls": []
        }
      },
      "looping": 0,
      "importantFrames": [],
      "firstFrameReturns": [],
      "lastFrameReturns": []
    }
  ],
  "IdleVariants": [
    {
      "priority": 0,
      "interruptibleBehaviour": 0,
      "forceSingleFrameAdvance": 0,
      "isUpgradeAnimation": 0,
      "animationClip": {
        "m_FileID": 0,
        "m_PathID": -6791877734444331704
      },
      "eventTrigger": {
        "m_PersistentCalls": {
          "m_Calls": []
        }
      },
      "looping": 0,
      "importantFrames": [],
      "firstFrameReturns": [],
      "lastFrameReturns": [],
      "variantWeight": 0.08
    },
    {
      "priority": 0,
      "interruptibleBehaviour": 0,
      "forceSingleFrameAdvance": 0,
      "isUpgradeAnimation": 0,
      "animationClip": {
        "m_FileID": 0,
        "m_PathID": -4182247809032067868
      },
      "eventTrigger": {
        "m_PersistentCalls": {
          "m_Calls": []
        }
      },
      "looping": 0,
      "importantFrames": [],
      "firstFrameReturns": [],
      "lastFrameReturns": [],
      "variantWeight": 0.08
    }
  ]
}